slark/__init__.py
slark/slark.py
slark/tests.py
slark-1.3.2.dist-info/METADATA
slark-1.3.2.dist-info/WHEEL
slark-1.3.2.dist-info/top_level.txt
slark-1.3.2.dist-info/RECORD
