Metadata-Version: 2.1
Name: slark
Version: 1.3.2
Summary: is a Simple, FileBase and Document Oriented database
Home-page: https://github.com/alirn76/slark
Author: Ali RajabNezhad
Author-email: alirn76@yahoo.com
License: MIT
Classifier: Operating System :: OS Independent
Classifier: License :: OSI Approved :: MIT License
Classifier: Programming Language :: Python :: 3.10
Classifier: Programming Language :: Python :: 3.11
Requires-Python: >=3.10
Requires-Dist: orjson (>=3.8.6)
